md99authtoken/__init__.py
md99authtoken/md99authtoken.py
md99authtoken/md99utils.py
md99authtoken-1.1.2.dist-info/License.txt
md99authtoken-1.1.2.dist-info/METADATA
md99authtoken-1.1.2.dist-info/WHEEL
md99authtoken-1.1.2.dist-info/top_level.txt
md99authtoken-1.1.2.dist-info/RECORD
