Metadata-Version: 2.2
Name: md99authtoken
Version: 1.1.2
Summary: Library for obtaining image Auth Token from MyDesign99 for python and django servers
Author: Tim Lambert
License: MIT License
Project-URL: Homepage, https://mydesign99.com
Project-URL: Documentation, https://mydesign99.com/documentation/intro
Project-URL: Repository, https://github.com/mydesign99/authtoken-sdk-python
Keywords: MyDesign99.com,MD99,authenticate,images,auth,token,sdk,python
Requires-Python: >=3.8
License-File: License.txt
